recordwright/__init__.py
recordwright/dndsim.js
recordwright/jquery-3.7.0.min.js
recordwright/play.js
recordwright/record.js
recordwright/replay.js
recordwright-1.0.1.dist-info/METADATA
recordwright-1.0.1.dist-info/WHEEL
recordwright-1.0.1.dist-info/top_level.txt
recordwright-1.0.1.dist-info/RECORD
